snakes_utils/__init__.py
snakes_utils/basic.py
snakes_utils/jss.py
snakes_utils/utils/__init__.py
snakes_utils/utils/utils.py
tests/__init__.py
tests/test_basic.py
tests/test_jss.py
snakes_utils-2.0.2.dist-info/COPYING
snakes_utils-2.0.2.dist-info/COPYING.LESSER
snakes_utils-2.0.2.dist-info/METADATA
snakes_utils-2.0.2.dist-info/WHEEL
snakes_utils-2.0.2.dist-info/top_level.txt
snakes_utils-2.0.2.dist-info/RECORD
