Metadata-Version: 2.1
Name: snakes-utils
Version: 2.0.2
Summary: Support conversion from SNAKES objects to Built-in Data Types in Python.
Home-page: https://github.com/kanekou/snakes_utils
Author: kanekou
Author-email: k208580@ie.u-ryukyu.ac.jp
License: LGPLv3+
Platform: UNKNOWN
Classifier: Programming Language :: Python :: 3.7
Classifier: License :: OSI Approved :: GNU Lesser General Public License v3 or later (LGPLv3+)
License-File: COPYING
License-File: COPYING.LESSER
Requires-Dist: snakes
